caccelerated.cpython-37m-darwin.so
profile.cpython-37m-darwin.so
trusat/__init__.py
trusat/caccelerated.cpython-37m-darwin.so
trusat/elfind.py
trusat/iod.py
trusat/profile.cpython-37m-darwin.so
trusat/satfit.py
trusat/satid.py
trusat/tle_util.py
trusat-0.9.0.dist-info/LICENSE
trusat-0.9.0.dist-info/METADATA
trusat-0.9.0.dist-info/WHEEL
trusat-0.9.0.dist-info/dependency_links.txt
trusat-0.9.0.dist-info/top_level.txt
trusat-0.9.0.dist-info/RECORD
