Metadata-Version: 2.1
Name: trusat
Version: 0.9.0
Summary: TruSat satellite observation processing utilities
Home-page: https://trusat.org/
Author: Chris Lewicki
Author-email: chris@lewicki.com
License: UNKNOWN
Project-URL: Source, https://github.com/TruSat/trusat-orbit
Project-URL: Tracker, https://github.com/TruSat/trusat-orbit/issues
Project-URL: Learning Hub, https://learn.trusat.org/docs/start-here
Project-URL: Forums, https://discuss.trusat.org/
Platform: UNKNOWN
Classifier: Development Status :: 4 - Beta
Classifier: Intended Audience :: Developers
Classifier: Intended Audience :: Science/Research
Classifier: License :: OSI Approved :: Apache Software License
Classifier: Natural Language :: English
Classifier: Operating System :: POSIX
Classifier: Operating System :: MacOS :: MacOS X
Classifier: Programming Language :: Python :: 3 :: Only
Classifier: Programming Language :: Python :: 3.6
Classifier: Programming Language :: Python :: 3.7
Classifier: Programming Language :: Python :: 3.8
Classifier: Programming Language :: Python :: Implementation :: CPython
Classifier: Topic :: Software Development :: Libraries :: Python Modules
Classifier: Topic :: Scientific/Engineering
Requires-Python: >=3.6
Requires-Dist: cython
Requires-Dist: numpy
Requires-Dist: sgp4 (>=2.7)
Requires-Dist: spacetrack
Requires-Dist: trusat-backend (==1.1.0)
